python_stl_example/__init__.py
python_stl_example/except_error.py
python_stl_example/stl_deque.py
python_stl_example/stl_list.py
python_stl_example/stl_set.py
python_stl_example/stl_stack.py
python_stl_example/stl_vector.py
python_stl_example-0.0.1.post2.dist-info/METADATA
python_stl_example-0.0.1.post2.dist-info/WHEEL
python_stl_example-0.0.1.post2.dist-info/top_level.txt
python_stl_example-0.0.1.post2.dist-info/RECORD
