Metadata-Version: 2.1
Name: python-stl-example
Version: 0.0.1.post2
Summary: A extended STL library
Home-page: https://github.com/fourth-dimensional/python_stl_example
Author: fourth-dimensional_universe
Author-email: 3817201131@qq.com
License: MIT
Classifier: Programming Language :: Python :: 3.5
Classifier: Programming Language :: Python :: 3.6
Classifier: Programming Language :: Python :: 3.7
Classifier: Programming Language :: Python :: 3.8
Classifier: Programming Language :: Python :: 3.9
Classifier: Programming Language :: Python :: 3.10
Classifier: Programming Language :: Python :: 3.11
Classifier: Programming Language :: Python :: 3.12
Classifier: License :: OSI Approved :: MIT License
Classifier: Operating System :: OS Independent
Requires-Python: >=3.5
